damv1telegramprojectk8salert/__init__.py
damv1telegramprojectk8salert/production_mytelegramproject.py
damv1telegramprojectk8salert/sandbox_mytelegramproject.py
damv1telegramprojectk8salert-0.0.8.dist-info/METADATA
damv1telegramprojectk8salert-0.0.8.dist-info/WHEEL
damv1telegramprojectk8salert-0.0.8.dist-info/top_level.txt
damv1telegramprojectk8salert-0.0.8.dist-info/RECORD
